spectralio/__init__.py
spectralio/_errors.py
spectralio/custom_types.py
spectralio/geospatial_models.py
spectralio/py.typed
spectralio/reading.py
spectralio/shapefiles.py
spectralio/spec1D_models.py
spectralio/spec3D_models.py
spectralio/specgroup_models.py
spectralio/writing.py
spectralio/wvl_models.py
spectralio-0.1.7.dist-info/licenses/LICENSE
spectralio-0.1.7.dist-info/METADATA
spectralio-0.1.7.dist-info/WHEEL
spectralio-0.1.7.dist-info/RECORD
