Metadata-Version: 2.4
Name: spectralio
Version: 0.1.7
Summary: Python-Optimized file formats for spectral data
License: LICENSE
License-File: LICENSE
Author: Z.M. Vig
Author-email: zvig@umd.edu
Requires-Python: >=3.13, <4
Classifier: License :: Other/Proprietary License
Classifier: Programming Language :: Python :: 3
Classifier: Programming Language :: Python :: 3.13
Classifier: Programming Language :: Python :: 3.14
Requires-Dist: alphashape (>=1.3.1,<2.0.0)
Requires-Dist: fiona (>=1.10.1,<2.0.0)
Requires-Dist: pydantic (>=2.12.4,<3.0.0)
Requires-Dist: rasterio (>=1.4.3,<2.0.0)
Requires-Dist: shapely (>=2.1.2,<3.0.0)
Requires-Dist: types-shapely (>=2.1.0.20250917,<3.0.0.0)
